hookpy/__init__.py
hookpy/__version__.py
hookpy/compat.py
hookpy/constants.py
hookpy/core.py
hookpy/funcid.py
hookpy/holdctx.py
hookpy/hookimport.py
hookpy/importer.py
hookpy/loader.py
hookpy/main.py
hookpy/testtools.py
hookpy/builtin_hooks/__init__.py
hookpy/builtin_hooks/functrace.py
hookpy-0.1.2.dist-info/LICENSE
hookpy-0.1.2.dist-info/METADATA
hookpy-0.1.2.dist-info/WHEEL
hookpy-0.1.2.dist-info/entry_points.txt
hookpy-0.1.2.dist-info/top_level.txt
hookpy-0.1.2.dist-info/RECORD
