Metadata-Version: 2.1
Name: hookpy
Version: 0.1.2
Summary: run python with custom hooks
Home-page: https://github.com/FindDefinition/hookpy
Author: Yan Yan
Author-email: yanyan.sub@outlook.com
License: MIT
Platform: UNKNOWN
Classifier: License :: OSI Approved :: MIT License
Classifier: Programming Language :: Python
Classifier: Programming Language :: Python :: 3
Classifier: Programming Language :: Python :: Implementation :: CPython
Classifier: Programming Language :: Python :: Implementation :: PyPy
Requires-Python: >=3.5
Requires-Dist: cachetools
Requires-Dist: pyyaml
